pyverify/__init__.py
pyverify/utils.py
pyverify/verify.py
pyverify_xnz233-1.1.2.dist-info/LICENSE
pyverify_xnz233-1.1.2.dist-info/METADATA
pyverify_xnz233-1.1.2.dist-info/WHEEL
pyverify_xnz233-1.1.2.dist-info/top_level.txt
pyverify_xnz233-1.1.2.dist-info/RECORD
