Metadata-Version: 2.1
Name: pyverify-xnz233
Version: 1.1.2
Summary: A small verify project
Home-page: https://github.com/xnz233/pyverify
Author: xnz233
Author-email: jl3362518@163.com
Classifier: Programming Language :: Python :: 3
Classifier: License :: OSI Approved :: MIT License
Classifier: Operating System :: OS Independent
Requires-Python: >=3.6
License-File: LICENSE
Requires-Dist: qrcode[pil]
Requires-Dist: pyotp
Requires-Dist: pillow
